zpca/__init__.py
zpca/zpca.py
zpca-0.8.3.post1.data/scripts/zpca-counts
zpca-0.8.3.post1.data/scripts/zpca-tpm
zpca-0.8.3.post1.dist-info/LICENSE
zpca-0.8.3.post1.dist-info/METADATA
zpca-0.8.3.post1.dist-info/WHEEL
zpca-0.8.3.post1.dist-info/top_level.txt
zpca-0.8.3.post1.dist-info/RECORD
