Metadata-Version: 2.1
Name: zpca
Version: 0.8.3.post1
Summary: PCA analysis for genes or transcripts.
Home-page: UNKNOWN
Author: Foivos Gypas
Author-email: fgypas@gmail.com
License: UNKNOWN
Keywords: zpca
Platform: UNKNOWN
Classifier: Programming Language :: Python :: 3.6
Requires-Dist: pandas (>=0.25)
Requires-Dist: scikit-learn (>=0.22)
Requires-Dist: matplotlib (>=3.1.3)
Requires-Dist: numpy (>=1.16)
